gitnote/__init__.py
gitnote/__init__.pyi
gitnote/commitgen/__init__.py
gitnote/commitgen/__init__.pyi
gitnote/commitgen/generator.py
gitnote/commitgen/generator.pyi
gitnote/commitgen/prompt.txt
gitnote/config/__init__.py
gitnote/config/__init__.pyi
gitnote/config/settings.py
gitnote/config/settings.pyi
gitnote/gittools/__init__.py
gitnote/gittools/__init__.pyi
gitnote/gittools/tools.py
gitnote/gittools/tools.pyi
gitnote/main.py
gitnote/main.pyi
gitnote/utils.py
gitnote/utils.pyi
gitnote-0.1.1.dist-info/METADATA
gitnote-0.1.1.dist-info/WHEEL
gitnote-0.1.1.dist-info/entry_points.txt
gitnote-0.1.1.dist-info/RECORD
