Metadata-Version: 2.1
Name: gitnote
Version: 0.1.1
Summary: AI-based Commit Generator Tool
Author: mostafa2k
Author-email: m2kappswindows8.1@gmail.com
Requires-Python: >=3.11,<4.0
Classifier: Programming Language :: Python :: 3
Classifier: Programming Language :: Python :: 3.11
Classifier: Programming Language :: Python :: 3.12
Classifier: Programming Language :: Python :: 3.13
Requires-Dist: huggingface-hub (>=0.26.3,<0.27.0)
Requires-Dist: keyring (>=25.5.0,<26.0.0)
Requires-Dist: mypy (>=1.13.0,<2.0.0)
Requires-Dist: pytest (>=8.3.4,<9.0.0)
Requires-Dist: pyyaml (>=6.0.2,<7.0.0)
Requires-Dist: ruamel-yaml (>=0.18.6,<0.19.0)
Requires-Dist: typer (>=0.14.0,<0.15.0)
